valkyrie_util/__init__.py
valkyrie_util/calculate.py
valkyrie_util/collatz.py
valkyrie_util/factors.py
valkyrie_util/fibonacci.py
valkyrie_util/large.py
valkyrie_util/primes.py
valkyrie_util/py.typed
valkyrie_util/triangle.py
valkyrie_util-2.3.3.dist-info/METADATA
valkyrie_util-2.3.3.dist-info/WHEEL
valkyrie_util-2.3.3.dist-info/top_level.txt
valkyrie_util-2.3.3.dist-info/RECORD
