Metadata-Version: 2.1
Name: valkyrie-util
Version: 2.3.3
Summary: A python library of various math and performance tools
Home-page: https://github.com/davidjcastner/valkyrie-util
Author: David Castner
Author-email: davidjcastner@gmail.com
License: UNKNOWN
Platform: UNKNOWN
Classifier: Development Status :: 5 - Production/Stable
Classifier: Intended Audience :: Developers
Classifier: License :: Other/Proprietary License
Classifier: Natural Language :: English
Classifier: Programming Language :: Python :: 3.8
Classifier: Topic :: Scientific/Engineering :: Mathematics
Requires-Python: >=3.8
